setup.py
pdb/__init__.py
pdbpy64.egg-info/PKG-INFO
pdbpy64.egg-info/SOURCES.txt
pdbpy64.egg-info/dependency_links.txt
pdbpy64.egg-info/top_level.txt