Metadata-Version: 1.0
Name: pdbpy64
Version: 0.0.2
Summary: Load, save, manage databases in python
Home-page: UNKNOWN
Author: UNKNOWN
Author-email: UNKNOWN
License: UNKNOWN
Platform: UNKNOWN
